CHANGES.txt
DEPENDENCES.txt
README.txt
setup.py
src/ng/__init__.py
src/ng.site.crosswiki.egg-info/PKG-INFO
src/ng.site.crosswiki.egg-info/SOURCES.txt
src/ng.site.crosswiki.egg-info/dependency_links.txt
src/ng.site.crosswiki.egg-info/namespace_packages.txt
src/ng.site.crosswiki.egg-info/not-zip-safe
src/ng.site.crosswiki.egg-info/requires.txt
src/ng.site.crosswiki.egg-info/top_level.txt
src/ng/site/__init__.py
src/ng/site/crosswiki/__init__.py
src/ng/site/crosswiki/configure.zcml
src/ng/site/crosswiki/ng.site.crosswiki.txt
src/ng/site/crosswiki/etc/ng.site.crosswiki-configure.zcml
src/ng/site/crosswiki/etc/ng.site.crosswiki-meta.zcml
src/ng/site/crosswiki/install/__init__.py
src/ng/site/crosswiki/install/configure.zcml